Workbook
Name aporte: projeto!$D$18
Name patrimonio: projeto!$D$21
Name qtd_anos: projeto!$D$19
Name renbdimento_carteira: projeto!$D$12
Name salario: projeto!$D$11
Name sugetao_investimento: projeto!$D$13
Name taxa_mensal: projeto!$D$20

Sheet projeto
B9: CONFIGURAÇÕES
B11: Salario | D11: 4200
B12: Rendimento carteita | D12: 0.006
B13: Sugestão de investimento(30%) | D13: =D11*30% -> 1260
B16: INVESTIMENTO MENSAL
B18: Quanto investir por mês? | D18: 1260
B19: Por quantos anos? | D19: 10
B20: Taxa de rendimento mensal? | D20: 0.01079
B21: Patrimônio acumulado? | D21: =FV(taxa_mensal,qtd_anos*12,aporte*-1) -> 306538.11
B22: Dividendo mensais? | D22: =patrimonio*renbdimento_carteira -> 1839.2286
B25: Cenários | D25: Dividendo
B27: Quanto em 2 anos? | C27: =FV($D$20,$A29*12,$D$18*-1) -> 34306.81 | D27: =C27*renbdimento_carteira -> 205.84086
B28: Quanto em 5 anos? | C28: =FV($D$20,$A30*12,$D$18*-1) -> 105558.91 | D28: =C28*renbdimento_carteira -> 633.35347
A29: 2 | B29: Quanto em 10 anos? | C29: =FV($D$20,$A31*12,$D$18*-1) -> 306538.11 | D29: =C29*renbdimento_carteira -> 1839.2286
A30: 5 | B30: Quanto em 20 anos? | C30: =FV($D$20,$A32*12,$D$18*-1) -> 1417750 | D30: =C30*renbdimento_carteira -> 8506.4999
A31: 10 | B31: Quanto em 30 anos? | C31: =FV($D$20,$A33*12,$D$18*-1) -> 5445933.8 | D31: =C31*renbdimento_carteira -> 32675.603
A32: 20
A33: 30
B34: PERFIL | C34: Moderado
B35: VALOR A SER INVESTIDO POR MÊS | C35: =aporte -> 1260
B37: TIPO DE FII | C37: Percentual Sugerido | D37: Valores
B38: PAPEL | C38: =VLOOKUP($C$34&"-"&B38,Planilha_apoio!$A:$D,4,FALSE) -> 0.32 | D38: =C38*$C$35 -> 403.2
B39: TIJOLO | C39: =VLOOKUP($C$34&"-"&B39,Planilha_apoio!$A:$D,4,FALSE) -> 0.35 | D39: =C39*$C$35 -> 441
B40: HÍBRIDOS | C40: =VLOOKUP($C$34&"-"&B40,Planilha_apoio!$A:$D,4,FALSE) -> 0.08 | D40: =C40*$C$35 -> 100.8
B41: FOFs | C41: =VLOOKUP($C$34&"-"&B41,Planilha_apoio!$A:$D,4,FALSE) -> 0.05 | D41: =C41*$C$35 -> 63
B42: DESENVOLVIMENTO | C42: =VLOOKUP($C$34&"-"&B42,Planilha_apoio!$A:$D,4,FALSE) -> 0.1 | D42: =C42*$C$35 -> 126
B43: HOTELARIAS | C43: =VLOOKUP($C$34&"-"&B43,Planilha_apoio!$A:$D,4,FALSE) -> 0.1 | D43: =C43*$C$35 -> 126
D44: =SUM(D38:D43) -> 1260

Sheet Planilha_apoio
A2: CHAVE | B2: PERFIL | C2: TIPO DE FII | D2: %
A3: =B3&"-"&C3 -> Conservador-PAPEL | B3: Conservador | C3: PAPEL | D3: 0.3
A4: =B4&"-"&C4 -> Conservador-TIJOLO | B4: Conservador | C4: TIJOLO | D4: 0.5
A5: =B5&"-"&C5 -> Conservador-HÍBRIDOS | B5: Conservador | C5: HÍBRIDOS | D5: 0.1
A6: =B6&"-"&C6 -> Conservador-FOFs | B6: Conservador | C6: FOFs | D6: 0.1
A7: =B7&"-"&C7 -> Conservador-DESENVOLVIMENTO | B7: Conservador | C7: DESENVOLVIMENTO | D7: 0
A8: =B8&"-"&C8 -> Conservador-HOTELARIAS | B8: Conservador | C8: HOTELARIAS | D8: 0
A9: =B9&"-"&C9 -> Moderado-PAPEL | B9: Moderado | C9: PAPEL | D9: 0.32
A10: =B10&"-"&C10 -> Moderado-TIJOLO | B10: Moderado | C10: TIJOLO | D10: 0.35
A11: =B11&"-"&C11 -> Moderado-HÍBRIDOS | B11: Moderado | C11: HÍBRIDOS | D11: 0.08
A12: =B12&"-"&C12 -> Moderado-FOFs | B12: Moderado | C12: FOFs | D12: 0.05
A13: =B13&"-"&C13 -> Moderado-DESENVOLVIMENTO | B13: Moderado | C13: DESENVOLVIMENTO | D13: 0.1
A14: =B14&"-"&C14 -> Moderado-HOTELARIAS | B14: Moderado | C14: HOTELARIAS | D14: 0.1
... A20: =B20&"-"&C20 -> Agressivo-HOTELARIAS | B20: Agressivo | C20: HOTELARIAS | D20: 0.1
